RedisDoc/README.md
RedisDoc/__init__.py
RedisDoc/__main__.py
RedisDoc/file.epub
RedisDoc/index.html
RedisDoc/css/__init__.py
RedisDoc/css/annotations.css
RedisDoc/css/main.css
RedisDoc/css/normalize.css
RedisDoc/css/popup.css
RedisDoc/font/__init__.py
RedisDoc/font/fontello.eot
RedisDoc/font/fontello.svg
RedisDoc/font/fontello.ttf
RedisDoc/font/fontello.woff
RedisDoc/img/__init__.py
RedisDoc/img/annotator-glyph-sprite.png
RedisDoc/img/annotator-icon-sprite.png
RedisDoc/img/apple-touch-icon.png
RedisDoc/img/cancelfullscreen.png
RedisDoc/img/close.png
RedisDoc/img/fullscreen.png
RedisDoc/img/loader.gif
RedisDoc/img/menu-icon.png
RedisDoc/img/save.png
RedisDoc/img/saved.png
RedisDoc/img/settings-s.png
RedisDoc/img/settings.png
RedisDoc/img/star.png
RedisDoc/js/__init__.py
RedisDoc/js/epub.js
RedisDoc/js/epub.min.js
RedisDoc/js/epub.min.map
RedisDoc/js/hooks.min.js
RedisDoc/js/hooks.min.map
RedisDoc/js/reader.js
RedisDoc/js/reader.js.map
RedisDoc/js/reader.min.js
RedisDoc/js/reader.min.map
RedisDoc/js/hooks/__init__.py
RedisDoc/js/hooks/extensions/__init__.py
RedisDoc/js/hooks/extensions/highlight.js
RedisDoc/js/libs/__init__.py
RedisDoc/js/libs/jquery.min.js
RedisDoc/js/libs/localforage.min.js
RedisDoc/js/libs/screenfull.js
RedisDoc/js/libs/screenfull.min.js
RedisDoc/js/libs/zip.min.js
RedisDoc/js/plugins/__init__.py
RedisDoc/js/plugins/hypothesis.js
RedisDoc/js/plugins/search.js
redis_doc-2024.3.1.0.dist-info/METADATA
redis_doc-2024.3.1.0.dist-info/WHEEL
redis_doc-2024.3.1.0.dist-info/entry_points.txt
redis_doc-2024.3.1.0.dist-info/top_level.txt
redis_doc-2024.3.1.0.dist-info/RECORD
